yta_testing/__init__.py
yta_testing-0.0.17.dist-info/licenses/LICENSE
yta_testing-0.0.17.dist-info/METADATA
yta_testing-0.0.17.dist-info/WHEEL
yta_testing-0.0.17.dist-info/RECORD
