Metadata-Version: 2.4
Name: yta-testing
Version: 0.0.17
Summary: Youtube Autonomous Testing Module
License-File: LICENSE
Author: danialcala94
Author-email: danielalcalavalera@gmail.com
Requires-Python: ==3.9
Classifier: Programming Language :: Python :: 3
Classifier: Programming Language :: Python :: 3.9
Requires-Dist: python-dotenv (>=0.0.1,<9.0.0)
